jenga_api_client-1.0.0.dist-info/licenses/LICENSE
jenga_client/__init__.py
jenga_client/api_client.py
jenga_client/api_response.py
jenga_client/configuration.py
jenga_client/exceptions.py
jenga_client/py.typed
jenga_client/rest.py
jenga_client/api/__init__.py
jenga_client/api/default_api.py
jenga_client/models/__init__.py
jenga_client/models/authentication_request.py
jenga_client/models/authentication_response.py
jenga_client/models/bill_payment_request.py
jenga_client/models/bill_payment_request_bill.py
jenga_client/models/bill_payment_request_biller.py
jenga_client/models/bill_payment_request_payer.py
jenga_client/models/bill_payment_response.py
jenga_client/models/bill_payment_response_data.py
jenga_client/models/bill_validation_request.py
jenga_client/models/bill_validation_response.py
jenga_client/models/bill_validation_response_data.py
jenga_client/models/biller.py
jenga_client/models/billers_response.py
jenga_client/models/eazzy_pay_merchant.py
jenga_client/models/eazzy_pay_merchant_outlets_inner.py
jenga_client/models/eazzy_pay_merchants_response.py
jenga_client/models/equitel_callback_response.py
jenga_client/models/equitel_push_request.py
jenga_client/models/equitel_push_request_merchant.py
jenga_client/models/equitel_push_request_payment.py
jenga_client/models/equitel_push_response.py
jenga_client/models/error.py
jenga_client/models/imt_within_equity_request.py
jenga_client/models/imt_within_equity_request_destination.py
jenga_client/models/imt_within_equity_request_sender.py
jenga_client/models/imt_within_equity_request_source.py
jenga_client/models/imt_within_equity_request_transfer.py
jenga_client/models/imt_within_equity_response.py
jenga_client/models/imt_within_equity_response_data.py
jenga_client/models/m_pesa_callback_response.py
jenga_client/models/m_pesa_callback_response_bank.py
jenga_client/models/m_pesa_callback_response_customer.py
jenga_client/models/m_pesa_callback_response_transaction.py
jenga_client/models/m_pesa_stk_push_request.py
jenga_api_client-1.0.0.dist-info/METADATA
jenga_api_client-1.0.0.dist-info/WHEEL
jenga_api_client-1.0.0.dist-info/top_level.txt
jenga_api_client-1.0.0.dist-info/RECORD
